justredis/__init__.py
justredis/decoder.py
justredis/encoder.py
justredis/errors.py
justredis/utils.py
justredis/nonsync/__init__.py
justredis/nonsync/cluster.py
justredis/nonsync/connection.py
justredis/nonsync/connectionpool.py
justredis/nonsync/environment.py
justredis/nonsync/redis.py
justredis/nonsync/environments/__init__.py
justredis/nonsync/environments/anyio.py
justredis/sync/__init__.py
justredis/sync/cluster.py
justredis/sync/connection.py
justredis/sync/connectionpool.py
justredis/sync/environment.py
justredis/sync/redis.py
justredis/sync/environments/__init__.py
justredis/sync/environments/threaded.py
tests/async/__init__.py
tests/async/conftest.py
tests/async/test_async.py
justredis-0.0.1a3.dist-info/LICENSE
justredis-0.0.1a3.dist-info/METADATA
justredis-0.0.1a3.dist-info/WHEEL
justredis-0.0.1a3.dist-info/top_level.txt
justredis-0.0.1a3.dist-info/RECORD
