Metadata-Version: 2.1
Name: justredis
Version: 0.0.1a3
Summary: A Redis client for Python supporting many Redis features and Python synchronous (Python 3.5+) and asynchronous (Python 3.6+) communication.
Home-page: https://github.com/tzickel/justredis
Author: tzickel
License: MIT
Project-URL: Source code, https://github.com/tzickel/justredis
Project-URL: Issue tracker, https://github.com/tzickel/justredis/issues
Keywords: redis
Platform: UNKNOWN
Classifier: Development Status :: 3 - Alpha
Classifier: License :: OSI Approved :: MIT License
Classifier: Programming Language :: Python :: Implementation :: CPython
Classifier: Programming Language :: Python :: Implementation :: PyPy
Classifier: Programming Language :: Python :: 3 :: Only
Classifier: Programming Language :: Python :: 3.5
Classifier: Programming Language :: Python :: 3.6
Classifier: Programming Language :: Python :: 3.7
Classifier: Programming Language :: Python :: 3.8
Requires-Python: >=3.5
